rhizotools/RP_IOfilecheck.py
rhizotools/RP_crop.py
rhizotools/RP_distmap.py
rhizotools/RP_distwindowrange.py
rhizotools/RP_imagefilter.py
rhizotools/RP_mask.py
rhizotools/RP_radwc.py
rhizotools/RP_remove.py
rhizotools/RP_rootimage.py
rhizotools/RP_run.py
rhizotools/RP_stitch.py
rhizotools/RP_thickness.py
rhizotools/RP_timerend.py
rhizotools/RP_timerprogress.py
rhizotools/RP_timerstart.py
rhizotools/RP_userconfiganalysis.py
rhizotools/RP_wc.py
rhizotools/RP_windowrange.py
rhizotools/__init__.py
rhizotools/_version.py
rhizotools/sampledata.py
rhizotools-0.3.0.dist-info/LICENSE
rhizotools-0.3.0.dist-info/METADATA
rhizotools-0.3.0.dist-info/WHEEL
rhizotools-0.3.0.dist-info/top_level.txt
rhizotools-0.3.0.dist-info/RECORD
