Metadata-Version: 2.2
Name: rhizotools
Version: 0.3.0
Summary: Python package for root processing images at MARS@ORNL
Author-email: Jean Bilheux <bilheuxjm@ornl.gov>, Chen Zhang <zhangc@ornl.gov>, Keita DeCarlo <decarlokd@ornl.gov>
License: MIT
Project-URL: homepage, https://github.com/ornlneutronimaging/RootPlantProcessing
Project-URL: repository, https://github.com/ornlneutronimaging/RootPlantProcessing
Project-URL: issues, https://github.com/ornlneutronimaging/RootPlantProcessing/issues
Keywords: root processing,neutron,biology,ORNL,MARS
Classifier: Development Status :: 4 - Beta
Classifier: Programming Language :: Python :: 3
Classifier: License :: OSI Approved :: MIT License
Classifier: Topic :: Scientific/Engineering :: Physics
Classifier: Intended Audience :: Science/Research
Requires-Python: >=3.11
License-File: LICENSE
Requires-Dist: numpy
Requires-Dist: astropy
Requires-Dist: scipy
Requires-Dist: pillow
Requires-Dist: scikit-image
